setup.py
pbbpm/__init__.py
pbbpm/__main__.py
pbbpm/pbbpm.py
pbbpm.egg-info/PKG-INFO
pbbpm.egg-info/SOURCES.txt
pbbpm.egg-info/dependency_links.txt
pbbpm.egg-info/top_level.txt