Metadata-Version: 1.1
Name: pbbpm
Version: 0.0.1
Summary: Python BitBucket Package Manager.
Home-page: https://github.com/AraHaan/pbbpm
Author: Decorater
Author-email: seandhunt_7@yahoo.com
License: MIT
Download-URL: https://github.com/AraHaan/pbbpm
Platform: Any
Classifier: Development Status :: 4 - Beta
Classifier: Intended Audience :: Developers
Classifier: License :: OSI Approved :: MIT License
Classifier: Natural Language :: English
Classifier: Operating System :: OS Independent
Classifier: Programming Language :: Python :: 3
Classifier: Topic :: Software Development :: Libraries
Classifier: Topic :: Software Development :: Libraries :: Python Modules
Classifier: Topic :: Utilities
